odoo8_addon_hr_payslip_move_date-8.0.0.1.0.99.dev8-nspkg.pth
odoo_addons/hr_payslip_move_date/README.rst
odoo_addons/hr_payslip_move_date/__init__.py
odoo_addons/hr_payslip_move_date/__openerp__.py
odoo_addons/hr_payslip_move_date/i18n/de.po
odoo_addons/hr_payslip_move_date/i18n/es.po
odoo_addons/hr_payslip_move_date/i18n/fr.po
odoo_addons/hr_payslip_move_date/i18n/hr_payslip_move_date.pot
odoo_addons/hr_payslip_move_date/i18n/sl.po
odoo_addons/hr_payslip_move_date/models/__init__.py
odoo_addons/hr_payslip_move_date/models/hr_payslip.py
odoo_addons/hr_payslip_move_date/static/description/icon.png
odoo_addons/hr_payslip_move_date/tests/__init__.py
odoo_addons/hr_payslip_move_date/tests/test_payslip.py
odoo_addons/hr_payslip_move_date/views/hr_payslip_view.xml
odoo_addons/hr_payslip_move_date/wizard/__init__.py
odoo_addons/hr_payslip_move_date/wizard/hr_payroll_payslips_by_employees.py
odoo8_addon_hr_payslip_move_date-8.0.0.1.0.99.dev8.dist-info/METADATA
odoo8_addon_hr_payslip_move_date-8.0.0.1.0.99.dev8.dist-info/WHEEL
odoo8_addon_hr_payslip_move_date-8.0.0.1.0.99.dev8.dist-info/namespace_packages.txt
odoo8_addon_hr_payslip_move_date-8.0.0.1.0.99.dev8.dist-info/top_level.txt
odoo8_addon_hr_payslip_move_date-8.0.0.1.0.99.dev8.dist-info/RECORD
